[
  {
    "id": 18571345,
    "name": "Facey Fifty - No 1 - Deep Lane",
    "number": 1
  },
  {
    "id": 18572319,
    "name": "Facey Fifty - No 2 - Scar Lane",
    "number": 2
  },
  {
    "id": 18571387,
    "name": "Facey Fifty - No 3 - Cowlersley Lane",
    "number": 3
  },
  {
    "id": 18571525,
    "name": "Facey Fifty - No 4 - Hoyle Ing",
    "number": 4
  },
  {
    "id": 18572259,
    "name": "Facey Fifty - No 5 - Lowestwood Lane/Copley Bank",
    "number": 5
  },
  {
    "id": 18571490,
    "name": "Facey Fifty - No 6 - Hoyle House/Causeway Side",
    "number": 6
  },
  {
    "id": 18571451,
    "name": "Facey Fifty - No 7 - Chapel Hill/Stones Lane/Upper Clough",
    "number": 7
  },
  {
    "id": 18572285,
    "name": "Facey Fifty - No 8 - Linfit lane/High House Edge",
    "number": 8
  },
  {
    "id": 18571590,
    "name": "Facey Fifty - No 9 - Varley Road",
    "number": 9
  },
  {
    "id": 18571624,
    "name": "Facey Fifty - No 10 - Yew Tree Lane",
    "number": 10
  },
  {
    "id": 18571612,
    "name": "Facey Fifty - No 11 - Lingards Road",
    "number": 11
  },
  {
    "id": 18572222,
    "name": "Facey Fifty - No 12 - Clough Road/Slaithwaite Gate",
    "number": 12
  },
  {
    "id": 18572153,
    "name": "Facey Fifty - No 13 - Meal Hill Lane",
    "number": 13
  },
  {
    "id": 18572179,
    "name": "Facey Fifty - No 14 - Bank Gate/Longlands Road/Heys Lane/Tiding Fields Lane/Pole Gate",
    "number": 14
  },
  {
    "id": 18572114,
    "name": "Facey Fifty - No 15 - Holme Lane",
    "number": 15
  },
  {
    "id": 18571859,
    "name": "Facey Fifty - No 16 - Shaw Fields Lane",
    "number": 16
  },
  {
    "id": 18571807,
    "name": "Facey Fifty - No 17 - Marsden Lane",
    "number": 17
  },
  {
    "id": 18571668,
    "name": "Facey Fifty - No 18 - Mount Road",
    "number": 18
  },
  {
    "id": 18571691,
    "name": "Facey Fifty - No 19 - Old Mount Road",
    "number": 19
  },
  {
    "id": 18571767,
    "name": "Facey Fifty - No 20 - Manchester Road (A62)",
    "number": 20
  },
  {
    "id": 18572369,
    "name": "Facey Fifty - No 21 - Lockwood Scar/Jackroyd Lane to Castle hill",
    "number": 21
  },
  {
    "id": 18572408,
    "name": "Facey Fifty - No 22 - Lady House Lane/Hall Bower Lane",
    "number": 22
  },
  {
    "id": 18572440,
    "name": "Facey Fifty - No 23 - Robin Hood Hill/Park Lane",
    "number": 23
  },
  {
    "id": 18583474,
    "name": "Facey Fifty - No 24 - Station Road/Northgate",
    "number": 24
  },
  {
    "id": 18572493,
    "name": "Facey Fifty - No 25 - Gynn Lane/Hall Ing Lane",
    "number": 25
  },
  {
    "id": 18583413,
    "name": "Facey Fifty - No 26 - Brockholes Lane",
    "number": 26
  },
  {
    "id": 18583530,
    "name": "Facey Fifty - No 27 - Thurstonland Bank",
    "number": 27
  },
  {
    "id": 18583605,
    "name": "Facey Fifty - No 28 - Cold Hill Lane",
    "number": 28
  },
  {
    "id": 18583546,
    "name": "Facey Fifty - No 29 - Sude Hill/Horn Lane",
    "number": 29
  },
  {
    "id": 18583496,
    "name": "Facey Fifty - No 30 - Penistone Road",
    "number": 30
  },
  {
    "id": 18583649,
    "name": "Facey Fifty - No 31 - Sheffield Road",
    "number": 31
  },
  {
    "id": 18918132,
    "name": "Facey Fifty - No 32 - South View, Jackson Bridge. Incorporating the (V9912)",
    "number": 32
  },
  {
    "id": 18586660,
    "name": "Facey Fifty - No 33 - Butt Lane/Dean Lane",
    "number": 33
  },
  {
    "id": 18583747,
    "name": "Facey Fifty - No 34 - Thong Lane",
    "number": 34
  },
  {
    "id": 18586720,
    "name": "Facey Fifty - No 35 - South Lane/Cinderhills Road",
    "number": 35
  },
  {
    "id": 18583788,
    "name": "Facey Fifty - No 36 - Dunford Road",
    "number": 36
  },
  {
    "id": 18589237,
    "name": "Facey Fifty - No 37 - Rotcher Road/Cycle Route 68",
    "number": 37
  },
  {
    "id": 18589271,
    "name": "Facey Fifty - No 38 - Upperthong Lane",
    "number": 38
  },
  {
    "id": 18589552,
    "name": "Facey Fifty - No 39 - Greenfield Road A635",
    "number": 39
  },
  {
    "id": 18589401,
    "name": "Facey Fifty - No 40 - Woodside View/Shaw Lane/Booth House Lane",
    "number": 40
  },
  {
    "id": 18589503,
    "name": "Facey Fifty - No 41 - Yew Tree Lane to A635",
    "number": 41
  },
  {
    "id": 18589442,
    "name": "Facey Fifty - No 42 - Dobb Lane/Woodhouse Lane",
    "number": 42
  },
  {
    "id": 18589353,
    "name": "Facey Fifty - No 43 - Field End Lane via Digley Reservoir to summit",
    "number": 43
  },
  {
    "id": 18589309,
    "name": "Facey Fifty - No 44 - Holme Moss (Full Climb)",
    "number": 44
  },
  {
    "id": 18595783,
    "name": "Facey Fifty - No 45 - Bradshaw Road",
    "number": 45
  },
  {
    "id": 18595885,
    "name": "Facey Fifty - No 46 - Knowle Lane",
    "number": 46
  },
  {
    "id": 18589595,
    "name": "Facey Fifty - No 47 - Acre Lane/Thick Hollins Road",
    "number": 47
  },
  {
    "id": 18589186,
    "name": "Facey Fifty - No 48 - Wessenden Head Road",
    "number": 48
  },
  {
    "id": 18595805,
    "name": "Facey Fifty - No 49 - Slaithwaite Road",
    "number": 49
  },
  {
    "id": 18595823,
    "name": "Facey Fifty - No 50 - Meltham Road (Big Valley)",
    "number": 50
  }
]
